Workbook
Name Slicer_Months__Date: #N/A

Sheet RawData
A1: Transaction_ID | B1: Date | C1: Customer_ID | D1: Customer_Name | E1: Product_ID | F1: Product_Name | G1: Category | H1: Quantity | I1: Unit_Price | J1: Payment_Method | K1: Region | L1: Customer_Segment | M1: Customer_Since | N1: Total_Amount
A2: TRX0155 | B2: 45393 | C2: CUST023 | D2: Paul Baker | E2: P009 | F2: Monitor | G2: Electronics | H2: 3 | I2: 1999.99 | J2: Cash | K2: Central | L2: Basic | M2: 44425 | N2: =H2*I2 -> 5999.97
A3: TRX0023 | B3: 45396 | C3: CUST013 | D3: Joseph Jackson | E3: P009 | F3: Monitor | G3: Electronics | H3: 3 | I3: 3599.99 | J3: Credit Card | K3: Central | L3: Premium | M3: 44575 | N3: =H3*I3 -> 10799.97
A4: TRX0139 | B4: 45399 | C4: CUST021 | D4: Kevin Scott | E4: P005 | F4: Blender | G4: Appliances | H4: 3 | I4: 2899.99 | J4: PayPal | K4: South | L4: Standard | M4: 45262 | N4: =H4*I4 -> 8699.97
A5: TRX0043 | B5: 45400 | C5: CUST046 | D5: Kathleen Bennett | E5: P005 | F5: Blender | G5: Appliances | H5: 3 | I5: 959.99 | J5: Cash | K5: North | L5: Premium | M5: 45114 | N5: =H5*I5 -> 2879.97
A6: TRX0212 | B6: 45400 | C6: CUST003 | D6: Michael Brown | E6: P008 | F6: Bookshelf | G6: Furniture | H6: 5 | I6: 149.99 | J6: Credit Card | K6: North | L6: Premium | M6: 45295 | N6: =H6*I6 -> 749.95
A7: TRX0092 | B7: 45403 | C7: CUST024 | D7: Dorothy Nelson | E7: P005 | F7: Blender | G7: Appliances | H7: 2 | I7: 29.99 | J7: Cash | K7: West | L7: Standard | M7: 44746 | N7: =H7*I7 -> 59.98
A8: TRX0193 | B8: 45403 | C8: CUST024 | D8: Dorothy Nelson | E8: P003 | F8: Headphones | G8: Electronics | H8: 5 | I8: 119.99 | J8: Credit Card | K8: Central | L8: Standard | M8: 44418 | N8: =H8*I8 -> 599.95
A9: TRX0240 | B9: 45403 | C9: CUST017 | D9: Charles Allen | E9: P005 | F9: Blender | G9: Appliances | H9: 20.004001 | I9: 49.99 | J9: Debit Card | K9: South | L9: Basic | M9: 45007 | N9: =H9*I9 -> 1000
A10: TRX0135 | B10: 45405 | C10: CUST009 | D10: Robert Thomas | E10: P001 | F10: Laptop | G10: Electronics | H10: 3 | I10: 899.99 | J10: PayPal | K10: East | L10: Standard | M10: 45299 | N10: =H10*I10 -> 2699.97
A11: TRX0185 | B11: 45408 | C11: CUST026 | D11: Karen Hill | E11: P005 | F11: Blender | G11: Appliances | H11: 3 | I11: 59.99 | J11: Cash | K11: West | L11: Premium | M11: 45207 | N11: =H11*I11 -> 179.97
A12: TRX0138 | B12: 45408 | C12: CUST022 | D12: Susan Green | E12: P008 | F12: Bookshelf | G12: Furniture | H12: 1 | I12: 149.99 | J12: Credit Card | K12: West | L12: Standard | M12: 45103 | N12: =H12*I12 -> 149.99
A13: TRX0209 | B13: 45408 | C13: CUST046 | D13: Kathleen Bennett | E13: P008 | F13: Bookshelf | G13: Furniture | H13: 5 | I13: 149.99 | J13: Debit Card | K13: North | L13: Basic | M13: 44830 | N13: =H13*I13 -> 749.95
... A251: TRX0064 | B251: 45758 | C251: CUST031 | D251: Steven Turner | E251: P010 | F251: Keyboard | G251: Electronics | H251: 3 | I251: 89.99 | J251: Debit Card | K251: North | L251: Premium | M251: 44878 | N251: =H251*I251 -> 269.97

Sheet DataAnalysis
A1: WHATIF Analysis (Scenario Manager) :- I created two scenarios - High price And Low price by chaning only unit price cell and the total amount chaned autoamtically. (Goal Seek) :- Goal Seek was done using cells H9 and N9 , where Quantity (H9) was the value that Goal Seek Adjusted to reach a target amount in (N9).
Q2: Date and Time Functions
G3: FILTER Function Returning Multiple Value | L3: Text Abbreviation
G4: Filter by Category | I4: Filter by Region | L4: Paul Baker | N4: =UPPER(LEFT(RawData!D2,1) & LEFT(RIGHT(RawData!D2,LEN(RawData!D2)-FIND(" ",RawData!D2)),1)) -> PB | Q4: Today | R4: =TODAY() -> 45986
Q5: Now | R5: =NOW() -> 45986.702
G6: Appliances | H6: {=SUM(_xlfn._xlws.FILTER(RawData!N2:N251, RawData!G2:G251 = DataAnalysis!G6))} -> 20318.77 | I6: East | J6: {=SUM(_xlfn._xlws.FILTER(RawData!N2:N251,RawData!K2:K251 = DataAnalysis!I6))} -> 59288.39 | L6: Time Stamp(NOW & Iterative) | Q6: DateDIF | R6: This function is not working in my excel version
L7: Changing cell | M7: Hello | Q7: EOMONTH | R7: =EOMONTH(Q3,0) -> 31
L8: Time Stamp | M8: =IF(M7<>"", IF(M8="", NOW(), M8), "") -> 45986.702
A11: Conditional Formating | I11: Linear Regression Using Data Analysis ToolPack
A12: Top 10 -Highlighted With Red | I12: SUMMARY OUTPUT
A13: Bottom 10 - Highlighted With Yellow
I14: Regression Statistics
I15: Multiple R | J15: 0.27278378
I16: R Square | J16: 0.07441099
I17: Adjusted R Square | J17: 0.070678776
I18: Standard Error | J18: 1294.4021
I19: Observations | J19: 250
I21: ANOVA
J22: df | K22: SS | L22: MS | M22: F | N22: Significance F
I23: Regression | J23: 1 | K23: 33404811 | L23: 33404811 | M23: 19.937494 | N23: 1.2158559e-05
I24: Residual | J24: 248 | K24: 4.1551827e+08 | L24: 1675476.9
A25: Scenario Summary | I25: Total | J25: 249 | K25: 4.4892309e+08
C26: Current Values: | D26: High Price | E26: Low Price
D27: Created by Gopi | E27: Created by Gopi | J27: Coefficients | K27: Standard Error | L27: t Stat | M27: P-value | N27: Lower 95% | O27: Upper 95% | P27: Lower 95.0% | Q27: Upper 95.0%
A28: Changing Cells: | I28: Intercept | J28: 367.56678 | K28: 168.52214 | L28: 2.1811186 | M28: 0.030114404 | N28: 35.649677 | O28: 699.48388 | P28: 35.649677 | Q28: 699.48388
B29: $I$2 | C29: 1999.99 | D29: 1999.99 | E29: 1999.99 | I29: X Variable 1 | J29: 213.54539 | K29: 47.824993 | L29: 4.4651421 | M29: 1.2158559e-05 | N29: 119.35045 | O29: 307.74033 | P29: 119.35045 | Q29: 307.74033
B30: $I$3 | C30: 3599.99 | D30: 3599.99 | E30: 3599.99
B31: $I$4 | C31: 2899.99 | D31: 2899.99 | E31: 2899.99
B32: $I$5 | C32: 959.99 | D32: 959.99 | E32: 959.99 | I32: GroupBy concepts to find High-Value Customers using formulas
B33: $I$7 | C33: 29.99 | D33: 29.99 | E33: 29.99 | I33: Total Revenue Per Customer_ID | L33: Total Revenue Per Product_ID
B34: $I$8 | C34: 119.99 | D34: 119.99 | E34: 119.99
B35: $I$9 | C35: 49.99 | D35: 49.99 | E35: 49.99 | I35: =SUMIFS(RawData!$N$2:$N$250, RawData!$C$2:$C$250, RawData!C2) -> 13559.74 | L35: =SUMIFS(RawData!$N$2:$N$250, RawData!$E$2:$E$250, RawData!E2) -> 37299.12
B36: $I$10 | C36: 899.99 | D36: 899.99 | E36: 899.99
A37: Result Cells:
B38: $P$2
A39: Notes: Current Values column represents values of changing cells at
A40: time Scenario Summary Report was created. Changing cells for each | I40: FREQUENTLY PURCHASED PRODUCTS
A41: scenario are highlighted in gray. | I41: Most Frequently purchased Product | L41: Most frequently Purchased Product_ID
I43: {=INDEX(RawData!F2:F250, MODE(MATCH(RawData!F2:F250, RawData!F2:F250, 0)))} -> Bookshelf | L43: {=INDEX(RawData!E2:E250, MODE(MATCH(RawData!E2:E250, RawData!E2:E250, 0)))} -> P008

Sheet Pivot Table
B1: PIVOT TABLES
B2: Sales By Payment Method | E2: Product Wise Total Quantity Sold | H2: Region Wise Sales Performance | K2: Monthly Revenue Trend
B5: Row Labels | C5: Sum of Total_Amount | E5: Row Labels | F5: Sum of Quantity | H5: Row Labels | I5: Sum of Total_Amount | K5: Row Labels | L5: Sum of Total_Amount
B6: Cash | C6: 65317.79 | E6: Blender | F6: 104.004 | H6: Central | I6: 56438.34 | K6: Jan | L6: 25799.15
B7: Credit Card | C7: 71347.96 | E7: P005 | F7: 104.004 | H7: East | I7: 59288.39 | K7: Feb | L7: 16069.38
B8: Debit Card | C8: 52938.34 | E8: Bookshelf | F8: 102 | H8: North | I8: 53508.31 | K8: Mar | L8: 19899.38
B9: PayPal | C9: 66718.41 | E9: P008 | F9: 102 | H9: South | I9: 45738.78 | K9: Apr | L9: 55029.19
B10: Grand Total | C10: 256322.5 | E10: Coffee Maker | F10: 39 | H10: West | I10: 41348.68 | K10: May | L10: 17039.35
E11: P004 | F11: 39 | H11: Grand Total | I11: 256322.5 | K11: Jun | L11: 19299.45
E12: Desk | F12: 78 | K12: Jul | L12: 18479.4
E13: P007 | F13: 78 | K13: Aug | L13: 15759.43
E14: Headphones | F14: 47 | K14: Sep | L14: 12989.51
E15: P003 | F15: 47 | K15: Oct | L15: 20609.52
E16: Keyboard | F16: 89 | K16: Nov | L16: 12309.44
E17: P010 | F17: 89 | K17: Dec | L17: 23039.3
E18: Laptop | F18: 75 | K18: Grand Total | L18: 256322.5
E19: P001 | F19: 75
E20: Monitor | F20: 88
E21: P009 | F21: 88
E22: Office Chair | F22: 52
E23: P006 | F23: 52
E24: Smartphone | F24: 96
E25: P002 | F25: 96
E26: Grand Total | F26: 770.004

Sheet DashBoard
A1: DASHBOARD
B3: MONTHLY REVENUE TREND | P3: Region Wise Sales Performance
AC6: Row Labels | AD6: Sum of Total_Amount
AC7: Central | AD7: 56438.34
B8: Row Labels | C8: Sum of Total_Amount | AC8: East | AD8: 59288.39
B9: Jan | C9: 25799.15 | AC9: North | AD9: 53508.31
B10: Feb | C10: 16069.38 | AC10: South | AD10: 45738.78
B11: Mar | C11: 19899.38 | AC11: West | AD11: 41348.68
B12: Apr | C12: 55029.19 | AC12: Grand Total | AD12: 256322.5
B13: May | C13: 17039.35
B14: Jun | C14: 19299.45
B15: Jul | C15: 18479.4
B16: Aug | C16: 15759.43
B17: Sep | C17: 12989.51
B18: Oct | C18: 20609.52
B19: Nov | C19: 12309.44
B20: Dec | C20: 23039.3
B21: Grand Total | C21: 256322.5
B27: Sales By Payment Method | P27: Product Wise Total Quantity Sold
L30: Row Labels | M30: Sum of Total_Amount | AC30: Row Labels | AD30: Sum of Quantity
L31: Cash | M31: 65317.79 | AC31: Blender | AD31: 104.004
L32: Credit Card | M32: 71347.96 | AC32: P005 | AD32: 104.004
L33: Debit Card | M33: 52938.34 | AC33: Bookshelf | AD33: 102
L34: PayPal | M34: 66718.41 | AC34: P008 | AD34: 102
L35: Grand Total | M35: 256322.5 | AC35: Coffee Maker | AD35: 39
AC36: P004 | AD36: 39
AC37: Desk | AD37: 78
AC38: P007 | AD38: 78
AC39: Headphones | AD39: 47
AC40: P003 | AD40: 47
AC41: Keyboard | AD41: 89
AC42: P010 | AD42: 89
AC43: Laptop | AD43: 75
AC44: P001 | AD44: 75
AC45: Monitor | AD45: 88
AC46: P009 | AD46: 88
AC47: Office Chair | AD47: 52
... AC51: Grand Total | AD51: 770.004
