Workbook
Name Slicer_Category: #N/A
Name Slicer_Gender: #N/A
Name Slicer_PaymentMode: #N/A
Name Slicer_Product: #N/A
Name Slicer_Region: #N/A

Sheet DataSheet
A1: TransactionID | B1: CustomerName | C1: Gender | D1: Age | E1: Product | F1: Category | G1: Quantity | H1: UnitPrice | I1: TotalPrice | J1: DiscountPercent | K1: FinalPrice | L1: Date | M1: Region | N1: PaymentMode
A2: T0001 | B2: Diya | C2: F | D2: 46 | E2: Headphones | F2: Electronics | G2: 2 | H2: 8422 | I2: =G2*H2 -> 16844 | J2: 0.05 | K2: 16001.8 | L2: 2024-11-07 | M2: South | N2: UPI
A3: T0002 | B3: Kabir | C3: M | D3: 44 | E3: Laptop | F3: Electronics | G3: 4 | H3: 10768 | I3: =G3*H3 -> 43072 | J3: 0.15 | K3: 36611.2 | L3: 2024-06-19 | M3: East | N3: Card
A4: T0003 | B4: Diya | C4: F | D4: 28 | E4: Mobile | F4: Electronics | G4: 1 | H4: 24016 | I4: =G4*H4 -> 24016 | J4: 0.15 | K4: 20413.6 | L4: 2024-12-16 | M4: East | N4: Cash
A5: T0004 | B5: Aisha | C5: F | D5: 56 | E5: Headphones | F5: Electronics | G5: 5 | H5: 9873 | I5: =G5*H5 -> 49365 | J5: 0.2 | K5: =I5-(I5*J5) -> 39492 | L5: 2024-04-03 | M5: West | N5: UPI
A6: T0005 | B6: Diya | C6: F | D6: 58 | E6: Shirt | F6: Fashion | G6: 4 | H6: 4657 | I6: =G6*H6 -> 18628 | J6: 0.05 | K6: =I6-(I6*J6) -> 17696.6 | L6: 2024-06-19 | M6: East | N6: NetBanking
A7: T0006 | B7: Aisha | C7: F | D7: 51 | E7: Mixer | F7: Home | G7: 1 | H7: 7249 | I7: =G7*H7 -> 7249 | J7: 0.2 | K7: =I7-(I7*J7) -> 5799.2 | L7: 2024-11-25 | M7: North | N7: Card
A8: T0007 | B8: Kabir | C8: M | D8: 50 | E8: Watch | F8: Accessories | G8: 4 | H8: 17007 | I8: =G8*H8 -> 68028 | J8: 0.2 | K8: =I8-(I8*J8) -> 54422.4 | L8: 2024-08-24 | M8: West | N8: UPI
A9: T0008 | B9: Siya | C9: F | D9: 22 | E9: Laptop | F9: Electronics | G9: 3 | H9: 9112 | I9: =G9*H9 -> 27336 | J9: 0.2 | K9: =I9-(I9*J9) -> 21868.8 | L9: 2024-09-14 | M9: East | N9: NetBanking
A10: T0009 | B10: Aarav | C10: M | D10: 18 | E10: Laptop | F10: Electronics | G10: 4 | H10: 29615 | I10: =G10*H10 -> 118460 | J10: 0.15 | K10: =I10-(I10*J10) -> 100691 | L10: 2024-09-09 | M10: North | N10: UPI
A11: T0010 | B11: Diya | C11: F | D11: 32 | E11: Headphones | F11: Electronics | G11: 1 | H11: 21295 | I11: =G11*H11 -> 21295 | J11: 0.1 | K11: =I11-(I11*J11) -> 19165.5 | L11: 2024-07-15 | M11: South | N11: Cash
A12: T0011 | B12: Diya | C12: F | D12: 24 | E12: Backpack | F12: Accessories | G12: 3 | H12: 9220 | I12: =G12*H12 -> 27660 | J12: 0 | K12: =I12-(I12*J12) -> 27660 | L12: 2024-04-16 | M12: North | N12: UPI
A13: T0012 | B13: Siya | C13: F | D13: 19 | E13: Shirt | F13: Fashion | G13: 4 | H13: 2088 | I13: =G13*H13 -> 8352 | J13: 0.15 | K13: =I13-(I13*J13) -> 7099.2 | L13: 2024-02-06 | M13: North | N13: Cash
A14: T0013 | B14: Aisha | C14: F | D14: 42 | E14: Watch | F14: Accessories | G14: 5 | H14: 1337 | I14: =G14*H14 -> 6685 | J14: 0.15 | K14: =I14-(I14*J14) -> 5682.25 | L14: 2024-06-02 | M14: South | N14: NetBanking
A15: T0014 | B15: Rohan | C15: M | D15: 56 | E15: Laptop | F15: Electronics | G15: 2 | H15: 14114 | I15: =G15*H15 -> 28228 | J15: 0.05 | K15: =I15-(I15*J15) -> 26816.6 | L15: 2024-05-02 | M15: South | N15: UPI
A16: T0015 | B16: Meera | C16: F | D16: 45 | E16: Mobile | F16: Electronics | G16: 1 | H16: 25590 | I16: =G16*H16 -> 25590 | J16: 0.2 | K16: =I16-(I16*J16) -> 20472 | L16: 2024-01-17 | M16: North | N16: UPI
... A201: T0200 | B201: Kabir | C201: M | D201: 26 | E201: Headphones | F201: Electronics | G201: 2 | H201: 2153 | I201: =G201*H201 -> 4306 | J201: 0.1 | K201: =I201-(I201*J201) -> 3875.4 | L201: 2024-07-20 | M201: South | N201: NetBanking

Sheet DataAnalysis
M1: VLOOKUP
B2: Date And Time Function | E2: Conditional Formatting | M2: T0003 | N2: =IFERROR(VLOOKUP(M2, DataSheet!A:K, 11, FALSE), "Not found") -> 20413.6
B3: Now | C3: =NOW() -> 45987.564 | E3: Top 10 Highest Final Price Highlighted with Red | P3: SUM IF
B4: Today | C4: =TODAY() -> 45987 | E4: Bottom 10 Lowest Final Price Highlighted with Yellow | M4: INDEX-MATCH | P4: Diya | Q4: =SUMIF(DataSheet!B:B, P4, DataSheet!K:K) -> 749070.4
B5: EOMonth | C5: =EOMONTH(A1,B1) -> 31 | M5: T0086 | N5: =IFERROR(INDEX(DataSheet!K:K, MATCH(M5, DataSheet!A:A, 0)), "Not found") -> 38214
M7: IF - CONDITION | P7: SUMIFS
M8: T0156 | N8: =IF(INDEX(DataSheet!K:K, MATCH(M8, DataSheet!A:A, 0)) > 20000, "High Sale", "Normal Sale") -> High Sale | P8: Fashion
P9: F | Q9: =SUMIFS(DataSheet!K:K, DataSheet!F:F, P8, DataSheet!C:C, P9) -> 1071034.8
P12: COUNTIF
P13: Home | Q13: =COUNTIF(DataSheet!F:F, P13) -> 18
P16: COUNTIFS
P17: Accessories
B18: SUMMARY OUTPUT | P18: M | Q18: =COUNTIFS(DataSheet!F:F, P17, DataSheet!C:C, P18) -> 19
B20: Regression Statistics
B21: Multiple R | C21: 0.5624097
B22: R Square | C22: 0.31630467 | M22: Scenario Summary
B23: Adjusted R Square | C23: 0.31285166 | O23: Current Values: | P23: Best Price | Q23: Worst Price | R23: Expected Price
B24: Standard Error | C24: 26941.054 | P24: Created by GOPI on 26-11-2025 | Q24: Created by GOPI on 26-11-2025 Modified by GOPI on 26-11-2025 | R24: Created by GOPI on 26-11-2025
B25: Observations | C25: 200 | M25: Changing Cells:
N26: $K$2 | O26: 16001.8 | P26: 14999.5 | Q26: 16001.8 | R26: 16001.8
B27: ANOVA | N27: $K$3 | O27: 36611.2 | P27: 36611.2 | Q27: 59999.5 | R27: 36611.2
C28: df | D28: SS | E28: MS | F28: F | G28: Significance F | N28: $K$4 | O28: 20413.6 | P28: 20413.6 | Q28: 20413.6 | R28: 11999.5
B29: Regression | C29: 1 | D29: 6.6487094e+10 | E29: 6.6487094e+10 | F29: 91.60268 | G29: 4.4650936e-18 | M29: Result Cells:
B30: Residual | C30: 198 | D30: 1.4371244e+11 | E30: 7.258204e+08 | N30: $P$4
B31: Total | C31: 199 | D31: 2.1019953e+11 | M31: Notes: Current Values column represents values of changing cells at
M32: time Scenario Summary Report was created. Changing cells for each
C33: Coefficients | D33: Standard Error | E33: t Stat | F33: P-value | G33: Lower 95% | H33: Upper 95% | I33: Lower 95.0% | J33: Upper 95.0% | M33: scenario are highlighted in gray.
B34: Intercept | C34: 84.753651 | D34: 4652.4987 | E34: 0.018216802 | F34: 0.98548424 | G34: -9090.0552 | H34: 9259.5625 | I34: -9090.0552 | J34: 9259.5625
B35: X Variable 1 | C35: 12835.634 | D35: 1341.1063 | E35: 9.5709289 | F35: 4.4650936e-18 | G35: 10190.948 | H35: 15480.319 | I35: 10190.948 | J35: 15480.319

Sheet PivotTables
B1: PIVOT TABLES
B4: Row Labels | C4: Sum of FinalPrice | F4: Row Labels | G4: Average of FinalPrice | J4: Row Labels | K4: Count of PaymentMode | N4: Row Labels | O4: Count of UnitPrice
B5: Accessories | C5: 2240292.4 | F5: East | G5: 31413.794 | J5: Backpack | K5: 25 | N5: Accessories | O5: 24
B6: Electronics | C6: 3333789.4 | F6: North | G6: 33311.733 | J6: Headphones | K6: 32 | N6: Electronics | O6: 26
B7: Fashion | C7: 1876558.6 | F7: South | G7: 50378.75 | J7: Laptop | K7: 26 | N7: Fashion | O7: 25
B8: Home | C8: 691266.45 | F8: West | G8: 19692.346 | J8: Mixer | K8: 18 | N8: Home | O8: 7
B9: Grand Total | C9: 8141906.8 | F9: Grand Total | G9: 31534.328 | J9: Mobile | K9: 25 | N9: Grand Total | O9: 82
J10: Shirt | K10: 24
J11: Shoes | K11: 27
J12: Watch | K12: 23
J13: Grand Total | K13: 200

Sheet Sheet7
A1: TransactionID | B1: CustomerName | C1: Gender | D1: Age | E1: Product | F1: Category | G1: Quantity | H1: UnitPrice | I1: TotalPrice | J1: DiscountPercent | K1: FinalPrice | L1: Date | M1: Region | N1: PaymentMode
A2: T0197 | B2: Vivaan | C2: M | D2: 43 | E2: Watch | F2: Accessories | G2: 4 | H2: 1675 | I2: 6700 | J2: 0.2 | K2: 5360 | L2: 2024-01-08 | M2: East | N2: Cash
A3: T0190 | B3: Arjun | C3: M | D3: 24 | E3: Watch | F3: Accessories | G3: 4 | H3: 11037 | I3: 44148 | J3: 0.1 | K3: 39733.2 | L3: 2024-08-06 | M3: South | N3: Card
A4: T0185 | B4: Diya | C4: F | D4: 48 | E4: Backpack | F4: Accessories | G4: 3 | H4: 9254 | I4: 27762 | J4: 0.2 | K4: 22209.6 | L4: 2024-06-12 | M4: West | N4: Card
A5: T0182 | B5: Aisha | C5: F | D5: 58 | E5: Backpack | F5: Accessories | G5: 4 | H5: 7554 | I5: 30216 | J5: 0.1 | K5: 27194.4 | L5: 2024-10-23 | M5: South | N5: Cash
A6: T0179 | B6: Meera | C6: F | D6: 38 | E6: Backpack | F6: Accessories | G6: 5 | H6: 21053 | I6: 105265 | J6: 0.05 | K6: 100001.75 | L6: 2024-11-21 | M6: South | N6: NetBanking
A7: T0178 | B7: Diya | C7: F | D7: 50 | E7: Watch | F7: Accessories | G7: 5 | H7: 17584 | I7: 87920 | J7: 0.05 | K7: 83524 | L7: 2024-09-20 | M7: West | N7: Cash
A8: T0007 | B8: Kabir | C8: Male | D8: 50 | E8: Watch | F8: Accessories | G8: 4 | H8: 17007 | I8: 68028 | J8: 0.2 | K8: 54422.4 | L8: 2024-08-24 | M8: West | N8: UPI
A9: T0174 | B9: Pooja | C9: F | D9: 28 | E9: Watch | F9: Accessories | G9: 5 | H9: 19422 | I9: 97110 | J9: 0 | K9: 97110 | L9: 2024-03-07 | M9: South | N9: UPI
A10: T0173 | B10: Rohan | C10: M | D10: 44 | E10: Backpack | F10: Accessories | G10: 5 | H10: 27824 | I10: 139120 | J10: 0.05 | K10: 132164 | L10: 2024-01-14 | M10: West | N10: Cash
A11: T0172 | B11: Aisha | C11: F | D11: 23 | E11: Backpack | F11: Accessories | G11: 1 | H11: 19462 | I11: 19462 | J11: 0.15 | K11: 16542.7 | L11: 2024-07-16 | M11: South | N11: UPI
A12: T0011 | B12: Diya | C12: Female | D12: 24 | E12: Backpack | F12: Accessories | G12: 3 | H12: 9220 | I12: 27660 | J12: 0 | K12: 27660 | L12: 2024-04-16 | M12: North | N12: UPI
A13: T0168 | B13: Aisha | C13: F | D13: 22 | E13: Backpack | F13: Accessories | G13: 1 | H13: 10873 | I13: 10873 | J13: 0.05 | K13: 10329.35 | L13: 2024-10-15 | M13: North | N13: NetBanking
... A49: T0050 | B49: Aisha | C49: F | D49: 57 | E49: Backpack | F49: Accessories | G49: 5 | H49: 24005 | I49: 120025 | J49: 0.2 | K49: 96020 | L49: 2024-04-20 | M49: East | N49: UPI

Sheet DashBoard
A1: DASHBOARD
B3: SUM OF FINAL PRICE ON PRODUCTS | Q3: COUNT OF UNIT PRICE PER CATEGORY
B27: COUNT BY PAYMENT-MODE ON PRODUCT | Q27: AVERAGE OF FINAL PRICE BY REGION

Sheet SummarySheet
A1: SUMMARY :- In this practical work, I used several Excel tools to analyze and understand the sales dataset. I began by applying date and time functions such as NOW(), TODAY(), EOMONTH(), and DATEDIF() to make the sheet dynamic and automatically update important values. I then used conditional formatting to highlight the top 10 highest and bottom 10 lowest Final Prices, making it easier to identify key transactions at a glance. To retrieve and classify data efficiently, I used lookup formulas including VLOOKUP, INDEX and MATCH, IF, and nested IF statements. These helped in searching values based on Transaction IDs and categorizing sales based on conditions. I also performed What-If Analysis using Scenario Manager and Goal Seek to understand how changes in price and discount affect the final results. Using SUMIF and COUNTIF, I calculated category-wise totals and counts. PivotTables were created to summarize data such as total quantity sold by category, sales by region, and monthly sales performance. Finally, I carried out a simple linear regression using Quantity as the X-axis and Final Price as the Y-axis to observe the relationship between how quantity sold affects the final price. Overall, these Excel techniques helped me analyze data more accurately, make comparisons, visualize patterns, and understand the dataset in a clear and organized way.
